[
   {
      "MonitoringRef" : "3010535",
      "RecordedAtTime" : "2017-03-25T08:17:51.4714343+01:00",
      "MonitoredVehicleJourney" : {
         "MonitoredCall" : {
            "AimedArrivalTime" : "2017-03-25T08:26:00+01:00",
            "AimedDepartureTime" : "2017-03-25T08:26:00+01:00",
            "ExpectedArrivalTime" : "2017-03-25T08:26:00+01:00",
            "ExpectedDepartureTime" : "2017-03-25T08:26:00+01:00",
            "DestinationDisplay" : "Kongskog",
            "DeparturePlatformName" : "1",
            "VisitNumber" : 0,
            "VehicleAtStop" : false
         },
         "FramedVehicleJourneyRef" : {
            "DatedVehicleJourneyRef" : "403010610",
            "DataFrameRef" : "2017-03-25"
         },
         "VehicleRef" : null,
         "InCongestion" : false,
         "Delay" : null,
         "DestinationRef" : "2330180",
         "OriginRef" : "3010618",
         "DestinationName" : "Kongskog",
         "TrainBlockPart" : null,
         "OriginName" : "Oslo Bussterminal (gateterm.)",
         "Monitored" : false,
         "OperatorRef" : null,
         "DestinationAimedArrivalTime" : "2017-03-25T09:28:00+01:00",
         "OriginAimedDepartureTime" : "2017-03-25T08:25:00+01:00",
         "BlockRef" : null,
         "DirectionRef" : null,
         "VehicleFeatureRef" : null,
         "VehicleMode" : 0,
         "VehicleJourneyName" : "403010610",
         "DirectionName" : null,
         "LineRef" : "301",
         "PublishedLineName" : "301"
      },
      "StopVisitNote" : [],
      "Extensions" : {
         "IsHub" : false,
         "Deviations" : [],
         "DepartureNamePreMapping" : "1",
         "LineColour" : "76A300",
         "OccupancyData" : null
      }
   },
   {
      "RecordedAtTime" : "2017-03-25T08:17:51.4714343+01:00",
      "MonitoringRef" : "3010535",
      "Extensions" : {
         "OccupancyData" : null,
         "LineColour" : "76A300",
         "DepartureNamePreMapping" : "1",
         "Deviations" : [],
         "IsHub" : false
      },
      "StopVisitNote" : [],
      "MonitoredVehicleJourney" : {
         "OriginName" : "Oslo Bussterminal (gateterm.)",
         "OperatorRef" : null,
         "Monitored" : false,
         "DestinationAimedArrivalTime" : "2017-03-25T09:32:00+01:00",
         "BlockRef" : null,
         "DirectionRef" : null,
         "OriginAimedDepartureTime" : "2017-03-25T08:37:00+01:00",
         "PublishedLineName" : "321",
         "LineRef" : "321",
         "DirectionName" : null,
         "VehicleFeatureRef" : null,
         "VehicleJourneyName" : "403210606",
         "VehicleMode" : 0,
         "VehicleRef" : null,
         "InCongestion" : false,
         "FramedVehicleJourneyRef" : {
            "DataFrameRef" : "2017-03-25",
            "DatedVehicleJourneyRef" : "403210606"
         },
         "MonitoredCall" : {
            "AimedArrivalTime" : "2017-03-25T08:38:00+01:00",
            "ExpectedArrivalTime" : "2017-03-25T08:38:00+01:00",
            "AimedDepartureTime" : "2017-03-25T08:38:00+01:00",
            "DestinationDisplay" : "Lillestrøm",
            "ExpectedDepartureTime" : "2017-03-25T08:38:00+01:00",
            "VisitNumber" : 0,
            "DeparturePlatformName" : "1",
            "VehicleAtStop" : false
         },
         "Delay" : null,
         "DestinationRef" : "2310301",
         "OriginRef" : "3010618",
         "DestinationName" : "Lillestrøm",
         "TrainBlockPart" : null
      }
   },
   {
      "MonitoringRef" : "3010535",
      "RecordedAtTime" : "2017-03-25T08:17:51.4714343+01:00",
      "MonitoredVehicleJourney" : {
         "MonitoredCall" : {
            "VehicleAtStop" : false,
            "AimedArrivalTime" : "2017-03-25T08:56:00+01:00",
            "ExpectedArrivalTime" : "2017-03-25T08:56:00+01:00",
            "AimedDepartureTime" : "2017-03-25T08:56:00+01:00",
            "ExpectedDepartureTime" : "2017-03-25T08:56:00+01:00",
            "DestinationDisplay" : "Hellerudhaugen",
            "DeparturePlatformName" : "1",
            "VisitNumber" : 0
         },
         "VehicleRef" : null,
         "FramedVehicleJourneyRef" : {
            "DataFrameRef" : "2017-03-25",
            "DatedVehicleJourneyRef" : "403010612"
         },
         "InCongestion" : false,
         "Delay" : null,
         "DestinationRef" : "2330220",
         "OriginRef" : "3010618",
         "DestinationName" : "Hellerudhaugen",
         "TrainBlockPart" : null,
         "OriginName" : "Oslo Bussterminal (gateterm.)",
         "OperatorRef" : null,
         "Monitored" : false,
         "DestinationAimedArrivalTime" : "2017-03-25T09:56:00+01:00",
         "BlockRef" : null,
         "OriginAimedDepartureTime" : "2017-03-25T08:55:00+01:00",
         "DirectionRef" : null,
         "VehicleFeatureRef" : null,
         "VehicleMode" : 0,
         "VehicleJourneyName" : "403010612",
         "DirectionName" : null,
         "LineRef" : "301",
         "PublishedLineName" : "301"
      },
      "Extensions" : {
         "IsHub" : false,
         "OccupancyData" : null,
         "Deviations" : [],
         "DepartureNamePreMapping" : "1",
         "LineColour" : "76A300"
      },
      "StopVisitNote" : []
   },
   {
      "RecordedAtTime" : "2017-03-25T08:17:51.4714343+01:00",
      "MonitoringRef" : "3010535",
      "StopVisitNote" : [],
      "Extensions" : {
         "OccupancyData" : null,
         "LineColour" : "76A300",
         "DepartureNamePreMapping" : "1",
         "Deviations" : [],
         "IsHub" : false
      },
      "MonitoredVehicleJourney" : {
         "Delay" : null,
         "MonitoredCall" : {
            "ExpectedArrivalTime" : "2017-03-25T09:08:00+01:00",
            "AimedDepartureTime" : "2017-03-25T09:08:00+01:00",
            "AimedArrivalTime" : "2017-03-25T09:08:00+01:00",
            "DeparturePlatformName" : "1",
            "VisitNumber" : 0,
            "ExpectedDepartureTime" : "2017-03-25T09:08:00+01:00",
            "DestinationDisplay" : "Lillestrøm",
            "VehicleAtStop" : false
         },
         "VehicleRef" : null,
         "InCongestion" : false,
         "FramedVehicleJourneyRef" : {
            "DatedVehicleJourneyRef" : "403210608",
            "DataFrameRef" : "2017-03-25"
         },
         "TrainBlockPart" : null,
         "DestinationName" : "Lillestrøm",
         "OriginRef" : "3010618",
         "DestinationRef" : "2310301",
         "Monitored" : false,
         "OperatorRef" : null,
         "OriginName" : "Oslo Bussterminal (gateterm.)",
         "VehicleFeatureRef" : null,
         "VehicleJourneyName" : "403210608",
         "DirectionName" : null,
         "VehicleMode" : 0,
         "LineRef" : "321",
         "PublishedLineName" : "321",
         "OriginAimedDepartureTime" : "2017-03-25T09:07:00+01:00",
         "BlockRef" : null,
         "DirectionRef" : null,
         "DestinationAimedArrivalTime" : "2017-03-25T10:02:00+01:00"
      }
   },
   {
      "MonitoringRef" : "3010535",
      "RecordedAtTime" : "2017-03-25T08:17:51.4714343+01:00",
      "MonitoredVehicleJourney" : {
         "VehicleFeatureRef" : null,
         "VehicleJourneyName" : "403010614",
         "VehicleMode" : 0,
         "DirectionName" : null,
         "LineRef" : "301",
         "PublishedLineName" : "301",
         "OriginAimedDepartureTime" : "2017-03-25T09:25:00+01:00",
         "BlockRef" : null,
         "DirectionRef" : null,
         "DestinationAimedArrivalTime" : "2017-03-25T10:28:00+01:00",
         "Monitored" : false,
         "OperatorRef" : null,
         "OriginName" : "Oslo Bussterminal (gateterm.)",
         "TrainBlockPart" : null,
         "DestinationName" : "Kongskog",
         "OriginRef" : "3010618",
         "DestinationRef" : "2330180",
         "Delay" : null,
         "MonitoredCall" : {
            "VehicleAtStop" : false,
            "DestinationDisplay" : "Kongskog",
            "ExpectedDepartureTime" : "2017-03-25T09:26:00+01:00",
            "DeparturePlatformName" : "1",
            "VisitNumber" : 0,
            "AimedArrivalTime" : "2017-03-25T09:26:00+01:00",
            "AimedDepartureTime" : "2017-03-25T09:26:00+01:00",
            "ExpectedArrivalTime" : "2017-03-25T09:26:00+01:00"
         },
         "VehicleRef" : null,
         "InCongestion" : false,
         "FramedVehicleJourneyRef" : {
            "DatedVehicleJourneyRef" : "403010614",
            "DataFrameRef" : "2017-03-25"
         }
      },
      "Extensions" : {
         "DepartureNamePreMapping" : "1",
         "Deviations" : [],
         "LineColour" : "76A300",
         "OccupancyData" : null,
         "IsHub" : false
      },
      "StopVisitNote" : []
   },
   {
      "RecordedAtTime" : "2017-03-25T08:17:51.4714343+01:00",
      "MonitoringRef" : "3010535",
      "StopVisitNote" : [],
      "Extensions" : {
         "LineColour" : "76A300",
         "Deviations" : [],
         "DepartureNamePreMapping" : "1",
         "OccupancyData" : null,
         "IsHub" : false
      },
      "MonitoredVehicleJourney" : {
         "DestinationRef" : "2310301",
         "OriginRef" : "3010618",
         "DestinationName" : "Lillestrøm",
         "TrainBlockPart" : null,
         "MonitoredCall" : {
            "DestinationDisplay" : "Lillestrøm",
            "ExpectedDepartureTime" : "2017-03-25T09:38:00+01:00",
            "DeparturePlatformName" : "1",
            "VisitNumber" : 0,
            "AimedArrivalTime" : "2017-03-25T09:38:00+01:00",
            "AimedDepartureTime" : "2017-03-25T09:38:00+01:00",
            "ExpectedArrivalTime" : "2017-03-25T09:38:00+01:00",
            "VehicleAtStop" : false
         },
         "FramedVehicleJourneyRef" : {
            "DataFrameRef" : "2017-03-25",
            "DatedVehicleJourneyRef" : "403210610"
         },
         "VehicleRef" : null,
         "InCongestion" : false,
         "Delay" : null,
         "DestinationAimedArrivalTime" : "2017-03-25T10:32:00+01:00",
         "OriginAimedDepartureTime" : "2017-03-25T09:37:00+01:00",
         "BlockRef" : null,
         "DirectionRef" : null,
         "VehicleFeatureRef" : null,
         "DirectionName" : null,
         "VehicleJourneyName" : "403210610",
         "VehicleMode" : 0,
         "LineRef" : "321",
         "PublishedLineName" : "321",
         "OriginName" : "Oslo Bussterminal (gateterm.)",
         "OperatorRef" : null,
         "Monitored" : false
      }
   },
   {
      "RecordedAtTime" : "2017-03-25T08:17:51.4714343+01:00",
      "MonitoringRef" : "3010535",
      "StopVisitNote" : [],
      "Extensions" : {
         "Deviations" : [],
         "DepartureNamePreMapping" : "1",
         "LineColour" : "76A300",
         "OccupancyData" : null,
         "IsHub" : false
      },
      "MonitoredVehicleJourney" : {
         "OriginRef" : "3010618",
         "DestinationRef" : "2330220",
         "TrainBlockPart" : null,
         "DestinationName" : "Hellerudhaugen",
         "Delay" : null,
         "VehicleRef" : null,
         "FramedVehicleJourneyRef" : {
            "DatedVehicleJourneyRef" : "403010616",
            "DataFrameRef" : "2017-03-25"
         },
         "InCongestion" : false,
         "MonitoredCall" : {
            "AimedArrivalTime" : "2017-03-25T09:56:00+01:00",
            "ExpectedArrivalTime" : "2017-03-25T09:56:00+01:00",
            "AimedDepartureTime" : "2017-03-25T09:56:00+01:00",
            "DestinationDisplay" : "Hellerudhaugen",
            "ExpectedDepartureTime" : "2017-03-25T09:56:00+01:00",
            "DeparturePlatformName" : "1",
            "VisitNumber" : 0,
            "VehicleAtStop" : false
         },
         "DestinationAimedArrivalTime" : "2017-03-25T10:56:00+01:00",
         "LineRef" : "301",
         "PublishedLineName" : "301",
         "DirectionName" : null,
         "VehicleFeatureRef" : null,
         "VehicleJourneyName" : "403010616",
         "VehicleMode" : 0,
         "BlockRef" : null,
         "OriginAimedDepartureTime" : "2017-03-25T09:55:00+01:00",
         "DirectionRef" : null,
         "OriginName" : "Oslo Bussterminal (gateterm.)",
         "OperatorRef" : null,
         "Monitored" : false
      }
   },
   {
      "StopVisitNote" : [],
      "Extensions" : {
         "IsHub" : false,
         "DepartureNamePreMapping" : "1",
         "Deviations" : [],
         "LineColour" : "76A300",
         "OccupancyData" : null
      },
      "MonitoredVehicleJourney" : {
         "OperatorRef" : null,
         "Monitored" : false,
         "OriginName" : "Oslo Bussterminal (gateterm.)",
         "PublishedLineName" : "321",
         "LineRef" : "321",
         "VehicleFeatureRef" : null,
         "VehicleJourneyName" : "403210612",
         "VehicleMode" : 0,
         "DirectionName" : null,
         "BlockRef" : null,
         "OriginAimedDepartureTime" : "2017-03-25T10:07:00+01:00",
         "DirectionRef" : null,
         "DestinationAimedArrivalTime" : "2017-03-25T11:02:00+01:00",
         "Delay" : null,
         "InCongestion" : false,
         "VehicleRef" : null,
         "FramedVehicleJourneyRef" : {
            "DatedVehicleJourneyRef" : "403210612",
            "DataFrameRef" : "2017-03-25"
         },
         "MonitoredCall" : {
            "VehicleAtStop" : false,
            "DestinationDisplay" : "Lillestrøm",
            "ExpectedDepartureTime" : "2017-03-25T10:08:00+01:00",
            "VisitNumber" : 0,
            "DeparturePlatformName" : "1",
            "AimedArrivalTime" : "2017-03-25T10:08:00+01:00",
            "AimedDepartureTime" : "2017-03-25T10:08:00+01:00",
            "ExpectedArrivalTime" : "2017-03-25T10:08:00+01:00"
         },
         "TrainBlockPart" : null,
         "DestinationName" : "Lillestrøm",
         "OriginRef" : "3010618",
         "DestinationRef" : "2310301"
      },
      "RecordedAtTime" : "2017-03-25T08:17:51.4714343+01:00",
      "MonitoringRef" : "3010535"
   }
]
