[
   {
      "MonitoredVehicleJourney" : {
         "DirectionName" : "1",
         "FramedVehicleJourneyRef" : {
            "DatedVehicleJourneyRef" : "50010",
            "DataFrameRef" : "2017-03-25"
         },
         "VehicleFeatureRef" : "",
         "DestinationName" : "Lambertseter via Sæter",
         "BlockRef" : "7501",
         "OperatorRef" : "Unibuss",
         "OriginRef" : "3011011",
         "Monitored" : false,
         "TrainBlockPart" : null,
         "DestinationRef" : "3011011",
         "OriginAimedDepartureTime" : "0001-01-01T00:00:00",
         "OriginName" : "Lambertseter T [buss]",
         "LineRef" : "75",
         "DestinationAimedArrivalTime" : "0001-01-01T00:00:00",
         "InCongestion" : false,
         "VehicleJourneyName" : "200750024",
         "MonitoredCall" : {
            "AimedDepartureTime" : "2017-03-25T09:18:00+01:00",
            "ExpectedDepartureTime" : "2017-03-25T09:18:00+01:00",
            "VehicleAtStop" : false,
            "AimedArrivalTime" : "2017-03-25T09:18:00+01:00",
            "DestinationDisplay" : "Lambertseter via Sæter",
            "DeparturePlatformName" : "1",
            "VisitNumber" : 6,
            "ExpectedArrivalTime" : "2017-03-25T09:18:00+01:00"
         },
         "VehicleMode" : 0,
         "PublishedLineName" : "75A",
         "VehicleRef" : null,
         "DirectionRef" : "1",
         "Delay" : "PT0S"
      },
      "RecordedAtTime" : "2017-03-25T08:18:31.305+01:00",
      "MonitoringRef" : "3010852",
      "Extensions" : {
         "OccupancyData" : null,
         "DepartureNamePreMapping" : "1",
         "Deviations" : [],
         "IsHub" : false,
         "LineColour" : "E60000"
      },
      "StopVisitNote" : []
   },
   {
      "Extensions" : {
         "DepartureNamePreMapping" : "2",
         "OccupancyData" : null,
         "IsHub" : false,
         "Deviations" : [],
         "LineColour" : "E60000"
      },
      "StopVisitNote" : [],
      "MonitoringRef" : "3010852",
      "RecordedAtTime" : "2017-03-25T08:18:31.5336925+01:00",
      "MonitoredVehicleJourney" : {
         "OriginName" : "Lambertseter T [buss]",
         "LineRef" : "75",
         "DestinationAimedArrivalTime" : "2017-03-25T09:56:00+01:00",
         "DestinationRef" : "3011011",
         "OriginAimedDepartureTime" : "2017-03-25T09:42:00+01:00",
         "InCongestion" : false,
         "VehicleJourneyName" : "200750027",
         "VehicleMode" : 0,
         "MonitoredCall" : {
            "ExpectedDepartureTime" : "2017-03-25T09:50:00+01:00",
            "AimedDepartureTime" : "2017-03-25T09:50:00+01:00",
            "ExpectedArrivalTime" : "2017-03-25T09:50:00+01:00",
            "VehicleAtStop" : false,
            "AimedArrivalTime" : "2017-03-25T09:50:00+01:00",
            "VisitNumber" : 0,
            "DeparturePlatformName" : "2",
            "DestinationDisplay" : "Lambertseter via Nordseter"
         },
         "Delay" : null,
         "PublishedLineName" : "75A",
         "DirectionRef" : null,
         "VehicleRef" : null,
         "DirectionName" : null,
         "BlockRef" : null,
         "FramedVehicleJourneyRef" : {
            "DataFrameRef" : "2017-03-25",
            "DatedVehicleJourneyRef" : "200750027"
         },
         "VehicleFeatureRef" : null,
         "DestinationName" : "Lambertseter via Nordseter",
         "OperatorRef" : null,
         "OriginRef" : "3011011",
         "TrainBlockPart" : null,
         "Monitored" : false
      }
   },
   {
      "MonitoringRef" : "3010852",
      "RecordedAtTime" : "2017-03-25T08:18:31.5336925+01:00",
      "MonitoredVehicleJourney" : {
         "BlockRef" : null,
         "VehicleFeatureRef" : null,
         "FramedVehicleJourneyRef" : {
            "DataFrameRef" : "2017-03-25",
            "DatedVehicleJourneyRef" : "200750030"
         },
         "DestinationName" : "Lambertseter via Sæter",
         "DirectionName" : null,
         "TrainBlockPart" : null,
         "Monitored" : false,
         "OperatorRef" : null,
         "OriginRef" : "3011011",
         "InCongestion" : false,
         "VehicleJourneyName" : "200750030",
         "OriginName" : "Lambertseter T [buss]",
         "DestinationAimedArrivalTime" : "2017-03-25T10:26:00+01:00",
         "LineRef" : "75",
         "DestinationRef" : "3011011",
         "OriginAimedDepartureTime" : "2017-03-25T10:12:00+01:00",
         "Delay" : null,
         "PublishedLineName" : "75A",
         "DirectionRef" : null,
         "VehicleRef" : null,
         "VehicleMode" : 0,
         "MonitoredCall" : {
            "ExpectedArrivalTime" : "2017-03-25T10:18:00+01:00",
            "AimedArrivalTime" : "2017-03-25T10:18:00+01:00",
            "VehicleAtStop" : false,
            "VisitNumber" : 0,
            "DeparturePlatformName" : "1",
            "DestinationDisplay" : "Lambertseter via Sæter",
            "ExpectedDepartureTime" : "2017-03-25T10:18:00+01:00",
            "AimedDepartureTime" : "2017-03-25T10:18:00+01:00"
         }
      },
      "StopVisitNote" : [],
      "Extensions" : {
         "LineColour" : "E60000",
         "Deviations" : [],
         "IsHub" : false,
         "OccupancyData" : null,
         "DepartureNamePreMapping" : "1"
      }
   }
]
