[
   {
      "RecordedAtTime" : "2017-03-25T08:20:01.737+01:00",
      "MonitoredVehicleJourney" : {
         "VehicleFeatureRef" : "",
         "InCongestion" : false,
         "MonitoredCall" : {
            "VisitNumber" : 27,
            "DeparturePlatformName" : "2",
            "AimedArrivalTime" : "2017-03-25T08:21:00+01:00",
            "VehicleAtStop" : false,
            "DestinationDisplay" : "Helsfyr T",
            "ExpectedDepartureTime" : "2017-03-25T08:22:49.018+01:00",
            "ExpectedArrivalTime" : "2017-03-25T08:22:49.018+01:00",
            "AimedDepartureTime" : "2017-03-25T08:21:00+01:00"
         },
         "OriginRef" : "3010911",
         "VehicleJourneyName" : "200760156",
         "DestinationRef" : "3011441",
         "BlockRef" : "7603",
         "DirectionName" : "2",
         "OriginName" : "Hauketo stasjon [buss]",
         "Delay" : "PT109S",
         "TrainBlockPart" : null,
         "DestinationName" : "Helsfyr T",
         "LineRef" : "76",
         "VehicleMode" : 0,
         "OriginAimedDepartureTime" : "0001-01-01T00:00:00",
         "DirectionRef" : "2",
         "OperatorRef" : "Unibuss",
         "DestinationAimedArrivalTime" : "0001-01-01T00:00:00",
         "FramedVehicleJourneyRef" : {
            "DatedVehicleJourneyRef" : "50110",
            "DataFrameRef" : "2017-03-25"
         },
         "Monitored" : true,
         "PublishedLineName" : "76",
         "VehicleRef" : "101215"
      },
      "MonitoringRef" : "3011522",
      "StopVisitNote" : [],
      "Extensions" : {
         "DepartureNamePreMapping" : "2",
         "IsHub" : false,
         "OccupancyData" : {
            "OccupancyAvailable" : true,
            "OccupancyPercentage" : 20
         },
         "Deviations" : [],
         "LineColour" : "E60000"
      }
   },
   {
      "MonitoringRef" : "3011522",
      "StopVisitNote" : [],
      "MonitoredVehicleJourney" : {
         "Delay" : "PT0S",
         "OriginName" : "Tamburveien",
         "BlockRef" : "5802",
         "DirectionName" : "1",
         "TrainBlockPart" : null,
         "InCongestion" : false,
         "VehicleFeatureRef" : "",
         "DestinationRef" : "3011521",
         "VehicleJourneyName" : "100580171",
         "OriginRef" : "3012135",
         "MonitoredCall" : {
            "VisitNumber" : 23,
            "DestinationDisplay" : "Tveita",
            "DeparturePlatformName" : "2",
            "AimedArrivalTime" : "2017-03-25T08:25:00+01:00",
            "VehicleAtStop" : false,
            "ExpectedArrivalTime" : "2017-03-25T08:25:00+01:00",
            "AimedDepartureTime" : "2017-03-25T08:25:00+01:00",
            "ExpectedDepartureTime" : "2017-03-25T08:25:00+01:00"
         },
         "FramedVehicleJourneyRef" : {
            "DataFrameRef" : "2017-03-25",
            "DatedVehicleJourneyRef" : "300109"
         },
         "VehicleRef" : "308029",
         "PublishedLineName" : "58",
         "Monitored" : true,
         "OriginAimedDepartureTime" : "0001-01-01T00:00:00",
         "VehicleMode" : 0,
         "LineRef" : "58",
         "DestinationName" : "Tveita",
         "OperatorRef" : "Norgesbuss",
         "DestinationAimedArrivalTime" : "0001-01-01T00:00:00",
         "DirectionRef" : "1"
      },
      "Extensions" : {
         "Deviations" : [
            {
               "ID" : 43009,
               "Header" : "Stoppestedet Nordpolen skole mot sentrum er flyttet"
            }
         ],
         "LineColour" : "E60000",
         "OccupancyData" : {
            "OccupancyPercentage" : 0,
            "OccupancyAvailable" : true
         },
         "DepartureNamePreMapping" : "2",
         "IsHub" : false
      },
      "RecordedAtTime" : "2017-03-25T08:20:01.737+01:00"
   },
   {
      "RecordedAtTime" : "2017-03-25T08:20:01.737+01:00",
      "Extensions" : {
         "OccupancyData" : {
            "OccupancyAvailable" : true,
            "OccupancyPercentage" : 0
         },
         "Deviations" : [],
         "LineColour" : "E60000",
         "IsHub" : false,
         "DepartureNamePreMapping" : "2"
      },
      "MonitoredVehicleJourney" : {
         "DirectionRef" : "2",
         "DestinationAimedArrivalTime" : "0001-01-01T00:00:00",
         "OperatorRef" : "Norgesbuss",
         "DestinationName" : "Tveita",
         "OriginAimedDepartureTime" : "0001-01-01T00:00:00",
         "VehicleMode" : 0,
         "LineRef" : "69",
         "Monitored" : true,
         "PublishedLineName" : "69",
         "VehicleRef" : "308074",
         "FramedVehicleJourneyRef" : {
            "DatedVehicleJourneyRef" : "302709",
            "DataFrameRef" : "2017-03-25"
         },
         "OriginRef" : "3011547",
         "MonitoredCall" : {
            "VisitNumber" : 20,
            "DestinationDisplay" : "Tveita",
            "AimedArrivalTime" : "2017-03-25T08:25:00+01:00",
            "VehicleAtStop" : false,
            "DeparturePlatformName" : "2",
            "AimedDepartureTime" : "2017-03-25T08:25:00+01:00",
            "ExpectedArrivalTime" : "2017-03-25T08:25:00+01:00",
            "ExpectedDepartureTime" : "2017-03-25T08:25:00+01:00"
         },
         "DestinationRef" : "3011521",
         "VehicleJourneyName" : "100690197",
         "VehicleFeatureRef" : "",
         "InCongestion" : false,
         "TrainBlockPart" : null,
         "Delay" : "PT0S",
         "BlockRef" : "6901",
         "OriginName" : "Ole Messelts vei",
         "DirectionName" : "2"
      },
      "StopVisitNote" : [],
      "MonitoringRef" : "3011522"
   },
   {
      "RecordedAtTime" : "2017-03-25T08:20:02.0668597+01:00",
      "MonitoringRef" : "3011522",
      "StopVisitNote" : [],
      "MonitoredVehicleJourney" : {
         "DirectionRef" : null,
         "OperatorRef" : null,
         "DestinationAimedArrivalTime" : "2017-03-25T09:08:00+01:00",
         "DestinationName" : "OSL-ekspressen",
         "LineRef" : "3621",
         "VehicleMode" : 0,
         "OriginAimedDepartureTime" : "2017-03-25T08:03:00+01:00",
         "Monitored" : false,
         "PublishedLineName" : "UE1",
         "VehicleRef" : null,
         "FramedVehicleJourneyRef" : {
            "DatedVehicleJourneyRef" : "236210108",
            "DataFrameRef" : "2017-03-25"
         },
         "MonitoredCall" : {
            "DestinationDisplay" : "OSL-ekspressen",
            "AimedArrivalTime" : "2017-03-25T08:28:00+01:00",
            "VehicleAtStop" : false,
            "DeparturePlatformName" : "1",
            "AimedDepartureTime" : "2017-03-25T08:28:00+01:00",
            "ExpectedArrivalTime" : "2017-03-25T08:28:00+01:00",
            "ExpectedDepartureTime" : "2017-03-25T08:28:00+01:00",
            "VisitNumber" : 0
         },
         "OriginRef" : "3010866",
         "VehicleJourneyName" : "236210108",
         "DestinationRef" : "2350301",
         "VehicleFeatureRef" : null,
         "InCongestion" : false,
         "TrainBlockPart" : null,
         "BlockRef" : null,
         "DirectionName" : null,
         "OriginName" : "Leirskallen",
         "Delay" : null
      },
      "Extensions" : {
         "OccupancyData" : null,
         "LineColour" : "949494",
         "Deviations" : [],
         "IsHub" : false,
         "DepartureNamePreMapping" : "1"
      }
   },
   {
      "Extensions" : {
         "LineColour" : "E60000",
         "Deviations" : [],
         "OccupancyData" : {
            "OccupancyAvailable" : true,
            "OccupancyPercentage" : 0
         },
         "IsHub" : false,
         "DepartureNamePreMapping" : "1"
      },
      "MonitoringRef" : "3011522",
      "StopVisitNote" : [],
      "MonitoredVehicleJourney" : {
         "Delay" : "PT79S",
         "BlockRef" : "7954",
         "OriginName" : "Holmlia stasjon [buss]",
         "DirectionName" : "2",
         "TrainBlockPart" : null,
         "VehicleFeatureRef" : "",
         "InCongestion" : false,
         "OriginRef" : "3010921",
         "MonitoredCall" : {
            "VisitNumber" : 36,
            "DestinationDisplay" : "Grorud T",
            "DeparturePlatformName" : "1",
            "VehicleAtStop" : false,
            "AimedArrivalTime" : "2017-03-25T08:33:00+01:00",
            "ExpectedArrivalTime" : "2017-03-25T08:34:19+01:00",
            "AimedDepartureTime" : "2017-03-25T08:33:00+01:00",
            "ExpectedDepartureTime" : "2017-03-25T08:34:19+01:00"
         },
         "DestinationRef" : "3011941",
         "VehicleJourneyName" : "200790188",
         "FramedVehicleJourneyRef" : {
            "DataFrameRef" : "2017-03-25",
            "DatedVehicleJourneyRef" : "50910"
         },
         "Monitored" : true,
         "PublishedLineName" : "79",
         "VehicleRef" : "101232",
         "DestinationName" : "Grorud T",
         "OriginAimedDepartureTime" : "0001-01-01T00:00:00",
         "VehicleMode" : 0,
         "LineRef" : "79",
         "DirectionRef" : "2",
         "DestinationAimedArrivalTime" : "0001-01-01T00:00:00",
         "OperatorRef" : "Unibuss"
      },
      "RecordedAtTime" : "2017-03-25T08:20:01.737+01:00"
   },
   {
      "Extensions" : {
         "Deviations" : [
            {
               "Header" : "Stoppestedet Nordpolen skole mot sentrum er flyttet",
               "ID" : 43009
            }
         ],
         "LineColour" : "E60000",
         "OccupancyData" : {
            "OccupancyAvailable" : true,
            "OccupancyPercentage" : 0
         },
         "DepartureNamePreMapping" : "1",
         "IsHub" : false
      },
      "StopVisitNote" : [],
      "MonitoringRef" : "3011522",
      "MonitoredVehicleJourney" : {
         "TrainBlockPart" : null,
         "BlockRef" : "5802",
         "OriginName" : "Tveita T (foran senteret)",
         "DirectionName" : "2",
         "Delay" : "PT0S",
         "MonitoredCall" : {
            "VisitNumber" : 2,
            "ExpectedArrivalTime" : "2017-03-25T08:37:00+01:00",
            "AimedDepartureTime" : "2017-03-25T08:37:00+01:00",
            "ExpectedDepartureTime" : "2017-03-25T08:37:00+01:00",
            "DestinationDisplay" : "Nydalen via Bjerke",
            "DeparturePlatformName" : "1",
            "VehicleAtStop" : false,
            "AimedArrivalTime" : "2017-03-25T08:37:00+01:00"
         },
         "OriginRef" : "3011521",
         "VehicleJourneyName" : "100580231",
         "DestinationRef" : "3012135",
         "VehicleFeatureRef" : "",
         "InCongestion" : false,
         "Monitored" : true,
         "PublishedLineName" : "58",
         "VehicleRef" : "308029",
         "FramedVehicleJourneyRef" : {
            "DatedVehicleJourneyRef" : "303109",
            "DataFrameRef" : "2017-03-25"
         },
         "DirectionRef" : "2",
         "DestinationAimedArrivalTime" : "0001-01-01T00:00:00",
         "OperatorRef" : "Norgesbuss",
         "DestinationName" : "Nydalen via Bjerke",
         "LineRef" : "58",
         "OriginAimedDepartureTime" : "0001-01-01T00:00:00",
         "VehicleMode" : 0
      },
      "RecordedAtTime" : "2017-03-25T08:20:01.737+01:00"
   },
   {
      "RecordedAtTime" : "2017-03-25T08:20:01.737+01:00",
      "MonitoredVehicleJourney" : {
         "VehicleRef" : "101212",
         "Monitored" : true,
         "PublishedLineName" : "76",
         "FramedVehicleJourneyRef" : {
            "DatedVehicleJourneyRef" : "50210",
            "DataFrameRef" : "2017-03-25"
         },
         "DestinationAimedArrivalTime" : "0001-01-01T00:00:00",
         "OperatorRef" : "Unibuss",
         "DirectionRef" : "2",
         "LineRef" : "76",
         "VehicleMode" : 0,
         "OriginAimedDepartureTime" : "0001-01-01T00:00:00",
         "DestinationName" : "Helsfyr T",
         "TrainBlockPart" : null,
         "OriginName" : "Hauketo stasjon [buss]",
         "BlockRef" : "7604",
         "DirectionName" : "2",
         "Delay" : "PT0S",
         "VehicleJourneyName" : "200760159",
         "DestinationRef" : "3011441",
         "MonitoredCall" : {
            "VisitNumber" : 27,
            "ExpectedArrivalTime" : "2017-03-25T08:51:00+01:00",
            "AimedDepartureTime" : "2017-03-25T08:51:00+01:00",
            "ExpectedDepartureTime" : "2017-03-25T08:51:00+01:00",
            "DestinationDisplay" : "Helsfyr T",
            "DeparturePlatformName" : "2",
            "AimedArrivalTime" : "2017-03-25T08:51:00+01:00",
            "VehicleAtStop" : false
         },
         "OriginRef" : "3010911",
         "InCongestion" : false,
         "VehicleFeatureRef" : ""
      },
      "StopVisitNote" : [],
      "MonitoringRef" : "3011522",
      "Extensions" : {
         "IsHub" : false,
         "DepartureNamePreMapping" : "2",
         "OccupancyData" : {
            "OccupancyPercentage" : 0,
            "OccupancyAvailable" : true
         },
         "LineColour" : "E60000",
         "Deviations" : []
      }
   },
   {
      "Extensions" : {
         "DepartureNamePreMapping" : "2",
         "IsHub" : false,
         "OccupancyData" : {
            "OccupancyPercentage" : 0,
            "OccupancyAvailable" : true
         },
         "Deviations" : [
            {
               "Header" : "Stoppestedet Nordpolen skole mot sentrum er flyttet",
               "ID" : 43009
            }
         ],
         "LineColour" : "E60000"
      },
      "MonitoredVehicleJourney" : {
         "DirectionRef" : "1",
         "OperatorRef" : "Norgesbuss",
         "DestinationAimedArrivalTime" : "0001-01-01T00:00:00",
         "DestinationName" : "Tveita",
         "VehicleMode" : 0,
         "OriginAimedDepartureTime" : "0001-01-01T00:00:00",
         "LineRef" : "58",
         "PublishedLineName" : "58",
         "Monitored" : true,
         "VehicleRef" : "308035",
         "FramedVehicleJourneyRef" : {
            "DataFrameRef" : "2017-03-25",
            "DatedVehicleJourneyRef" : "300209"
         },
         "OriginRef" : "3012135",
         "MonitoredCall" : {
            "VisitNumber" : 23,
            "DeparturePlatformName" : "2",
            "AimedArrivalTime" : "2017-03-25T08:55:00+01:00",
            "VehicleAtStop" : false,
            "DestinationDisplay" : "Tveita",
            "ExpectedDepartureTime" : "2017-03-25T08:55:00+01:00",
            "ExpectedArrivalTime" : "2017-03-25T08:55:00+01:00",
            "AimedDepartureTime" : "2017-03-25T08:55:00+01:00"
         },
         "DestinationRef" : "3011521",
         "VehicleJourneyName" : "100580173",
         "VehicleFeatureRef" : "",
         "InCongestion" : false,
         "TrainBlockPart" : null,
         "Delay" : "PT0S",
         "BlockRef" : "5801",
         "OriginName" : "Tamburveien",
         "DirectionName" : "1"
      },
      "StopVisitNote" : [],
      "MonitoringRef" : "3011522",
      "RecordedAtTime" : "2017-03-25T08:20:01.737+01:00"
   },
   {
      "StopVisitNote" : [],
      "MonitoringRef" : "3011522",
      "MonitoredVehicleJourney" : {
         "FramedVehicleJourneyRef" : {
            "DataFrameRef" : "2017-03-25",
            "DatedVehicleJourneyRef" : "51110"
         },
         "VehicleRef" : "101233",
         "PublishedLineName" : "79",
         "Monitored" : true,
         "LineRef" : "79",
         "VehicleMode" : 0,
         "OriginAimedDepartureTime" : "0001-01-01T00:00:00",
         "DestinationName" : "Grorud T",
         "OperatorRef" : "Unibuss",
         "DestinationAimedArrivalTime" : "0001-01-01T00:00:00",
         "DirectionRef" : "2",
         "DirectionName" : "2",
         "BlockRef" : "7955",
         "OriginName" : "Holmlia stasjon [buss]",
         "Delay" : "PT0S",
         "TrainBlockPart" : null,
         "InCongestion" : false,
         "VehicleFeatureRef" : "",
         "VehicleJourneyName" : "200790194",
         "DestinationRef" : "3011941",
         "MonitoredCall" : {
            "VisitNumber" : 36,
            "ExpectedDepartureTime" : "2017-03-25T09:03:00+01:00",
            "AimedDepartureTime" : "2017-03-25T09:03:00+01:00",
            "ExpectedArrivalTime" : "2017-03-25T09:03:00+01:00",
            "AimedArrivalTime" : "2017-03-25T09:03:00+01:00",
            "VehicleAtStop" : false,
            "DeparturePlatformName" : "1",
            "DestinationDisplay" : "Grorud T"
         },
         "OriginRef" : "3010921"
      },
      "Extensions" : {
         "OccupancyData" : {
            "OccupancyPercentage" : 0,
            "OccupancyAvailable" : true
         },
         "Deviations" : [],
         "LineColour" : "E60000",
         "IsHub" : false,
         "DepartureNamePreMapping" : "1"
      },
      "RecordedAtTime" : "2017-03-25T08:20:01.737+01:00"
   },
   {
      "RecordedAtTime" : "2017-03-25T08:20:02.0668597+01:00",
      "MonitoredVehicleJourney" : {
         "PublishedLineName" : "FB6",
         "Monitored" : false,
         "VehicleRef" : null,
         "FramedVehicleJourneyRef" : {
            "DataFrameRef" : "2017-03-25",
            "DatedVehicleJourneyRef" : "236060208"
         },
         "DirectionRef" : null,
         "OperatorRef" : null,
         "DestinationAimedArrivalTime" : "2017-03-25T09:44:00+01:00",
         "DestinationName" : "Oslo lufthavn",
         "LineRef" : "3606",
         "OriginAimedDepartureTime" : "2017-03-25T08:40:00+01:00",
         "VehicleMode" : 0,
         "TrainBlockPart" : null,
         "OriginName" : "Mortensrud T [buss]",
         "BlockRef" : null,
         "DirectionName" : null,
         "Delay" : null,
         "MonitoredCall" : {
            "VisitNumber" : 0,
            "AimedDepartureTime" : "2017-03-25T09:05:00+01:00",
            "ExpectedArrivalTime" : "2017-03-25T09:05:00+01:00",
            "ExpectedDepartureTime" : "2017-03-25T09:05:00+01:00",
            "DestinationDisplay" : "Oslo lufthavn",
            "VehicleAtStop" : false,
            "AimedArrivalTime" : "2017-03-25T09:05:00+01:00",
            "DeparturePlatformName" : "1"
         },
         "OriginRef" : "3010951",
         "VehicleJourneyName" : "236060208",
         "DestinationRef" : "2350301",
         "VehicleFeatureRef" : null,
         "InCongestion" : false
      },
      "StopVisitNote" : [],
      "MonitoringRef" : "3011522",
      "Extensions" : {
         "DepartureNamePreMapping" : "1",
         "IsHub" : false,
         "OccupancyData" : null,
         "LineColour" : "949494",
         "Deviations" : [
            {
               "Header" : "Feil i reiseplanlegger",
               "ID" : 42794
            }
         ]
      }
   },
   {
      "RecordedAtTime" : "2017-03-25T08:20:01.737+01:00",
      "Extensions" : {
         "Deviations" : [
            {
               "ID" : 43009,
               "Header" : "Stoppestedet Nordpolen skole mot sentrum er flyttet"
            }
         ],
         "LineColour" : "E60000",
         "OccupancyData" : {
            "OccupancyPercentage" : 0,
            "OccupancyAvailable" : true
         },
         "DepartureNamePreMapping" : "1",
         "IsHub" : false
      },
      "MonitoredVehicleJourney" : {
         "OperatorRef" : "Norgesbuss",
         "DestinationAimedArrivalTime" : "0001-01-01T00:00:00",
         "DirectionRef" : "2",
         "OriginAimedDepartureTime" : "0001-01-01T00:00:00",
         "VehicleMode" : 0,
         "LineRef" : "58",
         "DestinationName" : "Nydalen via Bjerke",
         "VehicleRef" : "308035",
         "PublishedLineName" : "58",
         "Monitored" : true,
         "FramedVehicleJourneyRef" : {
            "DatedVehicleJourneyRef" : "303209",
            "DataFrameRef" : "2017-03-25"
         },
         "DestinationRef" : "3012135",
         "VehicleJourneyName" : "100580233",
         "OriginRef" : "3011521",
         "MonitoredCall" : {
            "DeparturePlatformName" : "1",
            "AimedArrivalTime" : "2017-03-25T09:07:00+01:00",
            "VehicleAtStop" : false,
            "DestinationDisplay" : "Nydalen via Bjerke",
            "ExpectedDepartureTime" : "2017-03-25T09:07:00+01:00",
            "ExpectedArrivalTime" : "2017-03-25T09:07:00+01:00",
            "AimedDepartureTime" : "2017-03-25T09:07:00+01:00",
            "VisitNumber" : 2
         },
         "InCongestion" : false,
         "VehicleFeatureRef" : "",
         "TrainBlockPart" : null,
         "Delay" : "PT0S",
         "BlockRef" : "5801",
         "OriginName" : "Tveita T (foran senteret)",
         "DirectionName" : "2"
      },
      "MonitoringRef" : "3011522",
      "StopVisitNote" : []
   },
   {
      "StopVisitNote" : [],
      "MonitoringRef" : "3011522",
      "MonitoredVehicleJourney" : {
         "VehicleFeatureRef" : null,
         "InCongestion" : false,
         "OriginRef" : "3010911",
         "MonitoredCall" : {
            "DeparturePlatformName" : "2",
            "VehicleAtStop" : false,
            "AimedArrivalTime" : "2017-03-25T09:21:00+01:00",
            "DestinationDisplay" : "Helsfyr T",
            "ExpectedDepartureTime" : "2017-03-25T09:21:00+01:00",
            "ExpectedArrivalTime" : "2017-03-25T09:21:00+01:00",
            "AimedDepartureTime" : "2017-03-25T09:21:00+01:00",
            "VisitNumber" : 0
         },
         "DestinationRef" : "3011441",
         "VehicleJourneyName" : "200760162",
         "Delay" : null,
         "OriginName" : "Hauketo stasjon [buss]",
         "BlockRef" : null,
         "DirectionName" : null,
         "TrainBlockPart" : null,
         "DestinationName" : "Helsfyr T",
         "OriginAimedDepartureTime" : "2017-03-25T08:52:00+01:00",
         "VehicleMode" : 0,
         "LineRef" : "76",
         "DirectionRef" : null,
         "DestinationAimedArrivalTime" : "2017-03-25T09:29:00+01:00",
         "OperatorRef" : null,
         "FramedVehicleJourneyRef" : {
            "DataFrameRef" : "2017-03-25",
            "DatedVehicleJourneyRef" : "200760162"
         },
         "PublishedLineName" : "76",
         "Monitored" : false,
         "VehicleRef" : null
      },
      "Extensions" : {
         "LineColour" : "E60000",
         "Deviations" : [],
         "OccupancyData" : null,
         "DepartureNamePreMapping" : "2",
         "IsHub" : false
      },
      "RecordedAtTime" : "2017-03-25T08:20:02.0668597+01:00"
   },
   {
      "Extensions" : {
         "OccupancyData" : null,
         "LineColour" : "E60000",
         "Deviations" : [],
         "IsHub" : false,
         "DepartureNamePreMapping" : "2"
      },
      "StopVisitNote" : [],
      "MonitoringRef" : "3011522",
      "MonitoredVehicleJourney" : {
         "OriginAimedDepartureTime" : "2017-03-25T09:06:00+01:00",
         "VehicleMode" : 0,
         "LineRef" : "69",
         "DestinationName" : "Tveita",
         "OperatorRef" : null,
         "DestinationAimedArrivalTime" : "2017-03-25T09:27:00+01:00",
         "DirectionRef" : null,
         "FramedVehicleJourneyRef" : {
            "DatedVehicleJourneyRef" : "100690199",
            "DataFrameRef" : "2017-03-25"
         },
         "VehicleRef" : null,
         "Monitored" : false,
         "PublishedLineName" : "69",
         "InCongestion" : false,
         "VehicleFeatureRef" : null,
         "DestinationRef" : "3011521",
         "VehicleJourneyName" : "100690199",
         "OriginRef" : "3011547",
         "MonitoredCall" : {
            "DestinationDisplay" : "Tveita",
            "DeparturePlatformName" : "2",
            "AimedArrivalTime" : "2017-03-25T09:25:00+01:00",
            "VehicleAtStop" : false,
            "ExpectedArrivalTime" : "2017-03-25T09:25:00+01:00",
            "AimedDepartureTime" : "2017-03-25T09:25:00+01:00",
            "ExpectedDepartureTime" : "2017-03-25T09:25:00+01:00",
            "VisitNumber" : 0
         },
         "Delay" : null,
         "BlockRef" : null,
         "OriginName" : "Ole Messelts vei",
         "DirectionName" : null,
         "TrainBlockPart" : null
      },
      "RecordedAtTime" : "2017-03-25T08:20:02.0668597+01:00"
   },
   {
      "RecordedAtTime" : "2017-03-25T08:20:02.0668597+01:00",
      "Extensions" : {
         "LineColour" : "E60000",
         "Deviations" : [
            {
               "Header" : "Stoppestedet Nordpolen skole mot sentrum er flyttet",
               "ID" : 43009
            }
         ],
         "OccupancyData" : null,
         "IsHub" : false,
         "DepartureNamePreMapping" : "2"
      },
      "MonitoringRef" : "3011522",
      "StopVisitNote" : [],
      "MonitoredVehicleJourney" : {
         "Monitored" : false,
         "PublishedLineName" : "58",
         "VehicleRef" : null,
         "FramedVehicleJourneyRef" : {
            "DataFrameRef" : "2017-03-25",
            "DatedVehicleJourneyRef" : "100580175"
         },
         "DirectionRef" : null,
         "DestinationAimedArrivalTime" : "2017-03-25T09:26:00+01:00",
         "OperatorRef" : null,
         "DestinationName" : "Tveita",
         "LineRef" : "58",
         "VehicleMode" : 0,
         "OriginAimedDepartureTime" : "2017-03-25T08:58:00+01:00",
         "TrainBlockPart" : null,
         "OriginName" : "Tamburveien",
         "BlockRef" : null,
         "DirectionName" : null,
         "Delay" : null,
         "MonitoredCall" : {
            "VisitNumber" : 0,
            "ExpectedArrivalTime" : "2017-03-25T09:25:00+01:00",
            "AimedDepartureTime" : "2017-03-25T09:25:00+01:00",
            "ExpectedDepartureTime" : "2017-03-25T09:25:00+01:00",
            "DestinationDisplay" : "Tveita",
            "DeparturePlatformName" : "2",
            "VehicleAtStop" : false,
            "AimedArrivalTime" : "2017-03-25T09:25:00+01:00"
         },
         "OriginRef" : "3012135",
         "VehicleJourneyName" : "100580175",
         "DestinationRef" : "3011521",
         "VehicleFeatureRef" : null,
         "InCongestion" : false
      }
   },
   {
      "RecordedAtTime" : "2017-03-25T08:20:02.0668597+01:00",
      "MonitoringRef" : "3011522",
      "StopVisitNote" : [],
      "MonitoredVehicleJourney" : {
         "VehicleRef" : null,
         "Monitored" : false,
         "PublishedLineName" : "UE1",
         "FramedVehicleJourneyRef" : {
            "DataFrameRef" : "2017-03-25",
            "DatedVehicleJourneyRef" : "236210111"
         },
         "OperatorRef" : null,
         "DestinationAimedArrivalTime" : "2017-03-25T10:08:00+01:00",
         "DirectionRef" : null,
         "LineRef" : "3621",
         "VehicleMode" : 0,
         "OriginAimedDepartureTime" : "2017-03-25T09:03:00+01:00",
         "DestinationName" : "OSL-ekspressen",
         "TrainBlockPart" : null,
         "BlockRef" : null,
         "OriginName" : "Leirskallen",
         "DirectionName" : null,
         "Delay" : null,
         "VehicleJourneyName" : "236210111",
         "DestinationRef" : "2350301",
         "MonitoredCall" : {
            "VisitNumber" : 0,
            "DestinationDisplay" : "OSL-ekspressen",
            "DeparturePlatformName" : "1",
            "VehicleAtStop" : false,
            "AimedArrivalTime" : "2017-03-25T09:28:00+01:00",
            "ExpectedArrivalTime" : "2017-03-25T09:28:00+01:00",
            "AimedDepartureTime" : "2017-03-25T09:28:00+01:00",
            "ExpectedDepartureTime" : "2017-03-25T09:28:00+01:00"
         },
         "OriginRef" : "3010866",
         "InCongestion" : false,
         "VehicleFeatureRef" : null
      },
      "Extensions" : {
         "OccupancyData" : null,
         "LineColour" : "949494",
         "Deviations" : [],
         "DepartureNamePreMapping" : "1",
         "IsHub" : false
      }
   },
   {
      "RecordedAtTime" : "2017-03-25T08:20:02.0668597+01:00",
      "StopVisitNote" : [],
      "MonitoringRef" : "3011522",
      "MonitoredVehicleJourney" : {
         "InCongestion" : false,
         "VehicleFeatureRef" : null,
         "VehicleJourneyName" : "200610032",
         "DestinationRef" : "3011521",
         "MonitoredCall" : {
            "VisitNumber" : 0,
            "ExpectedDepartureTime" : "2017-03-25T09:28:00+01:00",
            "ExpectedArrivalTime" : "2017-03-25T09:28:00+01:00",
            "AimedDepartureTime" : "2017-03-25T09:28:00+01:00",
            "DeparturePlatformName" : "2",
            "VehicleAtStop" : false,
            "AimedArrivalTime" : "2017-03-25T09:28:00+01:00",
            "DestinationDisplay" : "Tveita T"
         },
         "OriginRef" : "3011536",
         "BlockRef" : null,
         "OriginName" : "Solfjellet",
         "DirectionName" : null,
         "Delay" : null,
         "TrainBlockPart" : null,
         "LineRef" : "61",
         "OriginAimedDepartureTime" : "2017-03-25T09:21:00+01:00",
         "VehicleMode" : 0,
         "DestinationName" : "Tveita T",
         "OperatorRef" : null,
         "DestinationAimedArrivalTime" : "2017-03-25T09:31:00+01:00",
         "DirectionRef" : null,
         "FramedVehicleJourneyRef" : {
            "DatedVehicleJourneyRef" : "200610032",
            "DataFrameRef" : "2017-03-25"
         },
         "VehicleRef" : null,
         "PublishedLineName" : "61A",
         "Monitored" : false
      },
      "Extensions" : {
         "Deviations" : [],
         "LineColour" : "E60000",
         "OccupancyData" : null,
         "IsHub" : false,
         "DepartureNamePreMapping" : "2"
      }
   },
   {
      "Extensions" : {
         "OccupancyData" : null,
         "LineColour" : "E60000",
         "Deviations" : [],
         "IsHub" : false,
         "DepartureNamePreMapping" : "1"
      },
      "MonitoredVehicleJourney" : {
         "DirectionRef" : null,
         "OperatorRef" : null,
         "DestinationAimedArrivalTime" : "2017-03-25T09:56:00+01:00",
         "DestinationName" : "Grorud T",
         "VehicleMode" : 0,
         "OriginAimedDepartureTime" : "2017-03-25T08:59:00+01:00",
         "LineRef" : "79",
         "PublishedLineName" : "79",
         "Monitored" : false,
         "VehicleRef" : null,
         "FramedVehicleJourneyRef" : {
            "DatedVehicleJourneyRef" : "200790200",
            "DataFrameRef" : "2017-03-25"
         },
         "OriginRef" : "3010921",
         "MonitoredCall" : {
            "ExpectedDepartureTime" : "2017-03-25T09:33:00+01:00",
            "ExpectedArrivalTime" : "2017-03-25T09:33:00+01:00",
            "AimedDepartureTime" : "2017-03-25T09:33:00+01:00",
            "DeparturePlatformName" : "1",
            "VehicleAtStop" : false,
            "AimedArrivalTime" : "2017-03-25T09:33:00+01:00",
            "DestinationDisplay" : "Grorud T",
            "VisitNumber" : 0
         },
         "DestinationRef" : "3011941",
         "VehicleJourneyName" : "200790200",
         "VehicleFeatureRef" : null,
         "InCongestion" : false,
         "TrainBlockPart" : null,
         "Delay" : null,
         "OriginName" : "Holmlia stasjon [buss]",
         "BlockRef" : null,
         "DirectionName" : null
      },
      "StopVisitNote" : [],
      "MonitoringRef" : "3011522",
      "RecordedAtTime" : "2017-03-25T08:20:02.0668597+01:00"
   },
   {
      "Extensions" : {
         "OccupancyData" : null,
         "Deviations" : [
            {
               "ID" : 43009,
               "Header" : "Stoppestedet Nordpolen skole mot sentrum er flyttet"
            }
         ],
         "LineColour" : "E60000",
         "IsHub" : false,
         "DepartureNamePreMapping" : "1"
      },
      "MonitoringRef" : "3011522",
      "StopVisitNote" : [],
      "MonitoredVehicleJourney" : {
         "FramedVehicleJourneyRef" : {
            "DatedVehicleJourneyRef" : "100580235",
            "DataFrameRef" : "2017-03-25"
         },
         "PublishedLineName" : "58",
         "Monitored" : false,
         "VehicleRef" : null,
         "DestinationName" : "Nydalen via Bjerke",
         "LineRef" : "58",
         "VehicleMode" : 0,
         "OriginAimedDepartureTime" : "2017-03-25T09:35:00+01:00",
         "DirectionRef" : null,
         "OperatorRef" : null,
         "DestinationAimedArrivalTime" : "2017-03-25T10:04:00+01:00",
         "BlockRef" : null,
         "DirectionName" : null,
         "OriginName" : "Tveita T (foran senteret)",
         "Delay" : null,
         "TrainBlockPart" : null,
         "VehicleFeatureRef" : null,
         "InCongestion" : false,
         "MonitoredCall" : {
            "VisitNumber" : 0,
            "DestinationDisplay" : "Nydalen via Bjerke",
            "DeparturePlatformName" : "1",
            "AimedArrivalTime" : "2017-03-25T09:37:00+01:00",
            "VehicleAtStop" : false,
            "ExpectedArrivalTime" : "2017-03-25T09:37:00+01:00",
            "AimedDepartureTime" : "2017-03-25T09:37:00+01:00",
            "ExpectedDepartureTime" : "2017-03-25T09:37:00+01:00"
         },
         "OriginRef" : "3011521",
         "VehicleJourneyName" : "100580235",
         "DestinationRef" : "3012135"
      },
      "RecordedAtTime" : "2017-03-25T08:20:02.0668597+01:00"
   },
   {
      "Extensions" : {
         "IsHub" : false,
         "DepartureNamePreMapping" : "2",
         "OccupancyData" : null,
         "Deviations" : [],
         "LineColour" : "E60000"
      },
      "MonitoredVehicleJourney" : {
         "FramedVehicleJourneyRef" : {
            "DataFrameRef" : "2017-03-25",
            "DatedVehicleJourneyRef" : "200760165"
         },
         "PublishedLineName" : "76",
         "Monitored" : false,
         "VehicleRef" : null,
         "DestinationName" : "Helsfyr T",
         "VehicleMode" : 0,
         "OriginAimedDepartureTime" : "2017-03-25T09:22:00+01:00",
         "LineRef" : "76",
         "DirectionRef" : null,
         "DestinationAimedArrivalTime" : "2017-03-25T09:59:00+01:00",
         "OperatorRef" : null,
         "Delay" : null,
         "BlockRef" : null,
         "OriginName" : "Hauketo stasjon [buss]",
         "DirectionName" : null,
         "TrainBlockPart" : null,
         "VehicleFeatureRef" : null,
         "InCongestion" : false,
         "OriginRef" : "3010911",
         "MonitoredCall" : {
            "ExpectedArrivalTime" : "2017-03-25T09:51:00+01:00",
            "AimedDepartureTime" : "2017-03-25T09:51:00+01:00",
            "ExpectedDepartureTime" : "2017-03-25T09:51:00+01:00",
            "DestinationDisplay" : "Helsfyr T",
            "DeparturePlatformName" : "2",
            "AimedArrivalTime" : "2017-03-25T09:51:00+01:00",
            "VehicleAtStop" : false,
            "VisitNumber" : 0
         },
         "DestinationRef" : "3011441",
         "VehicleJourneyName" : "200760165"
      },
      "StopVisitNote" : [],
      "MonitoringRef" : "3011522",
      "RecordedAtTime" : "2017-03-25T08:20:02.0668597+01:00"
   },
   {
      "RecordedAtTime" : "2017-03-25T08:20:02.0668597+01:00",
      "Extensions" : {
         "Deviations" : [
            {
               "Header" : "Stoppestedet Nordpolen skole mot sentrum er flyttet",
               "ID" : 43009
            }
         ],
         "LineColour" : "E60000",
         "OccupancyData" : null,
         "IsHub" : false,
         "DepartureNamePreMapping" : "2"
      },
      "StopVisitNote" : [],
      "MonitoringRef" : "3011522",
      "MonitoredVehicleJourney" : {
         "BlockRef" : null,
         "DirectionName" : null,
         "OriginName" : "Tamburveien",
         "Delay" : null,
         "TrainBlockPart" : null,
         "InCongestion" : false,
         "VehicleFeatureRef" : null,
         "VehicleJourneyName" : "100580177",
         "DestinationRef" : "3011521",
         "MonitoredCall" : {
            "VisitNumber" : 0,
            "VehicleAtStop" : false,
            "AimedArrivalTime" : "2017-03-25T09:55:00+01:00",
            "DeparturePlatformName" : "2",
            "DestinationDisplay" : "Tveita",
            "ExpectedDepartureTime" : "2017-03-25T09:55:00+01:00",
            "AimedDepartureTime" : "2017-03-25T09:55:00+01:00",
            "ExpectedArrivalTime" : "2017-03-25T09:55:00+01:00"
         },
         "OriginRef" : "3012135",
         "FramedVehicleJourneyRef" : {
            "DataFrameRef" : "2017-03-25",
            "DatedVehicleJourneyRef" : "100580177"
         },
         "VehicleRef" : null,
         "Monitored" : false,
         "PublishedLineName" : "58",
         "LineRef" : "58",
         "VehicleMode" : 0,
         "OriginAimedDepartureTime" : "2017-03-25T09:28:00+01:00",
         "DestinationName" : "Tveita",
         "OperatorRef" : null,
         "DestinationAimedArrivalTime" : "2017-03-25T09:56:00+01:00",
         "DirectionRef" : null
      }
   },
   {
      "RecordedAtTime" : "2017-03-25T08:20:02.0668597+01:00",
      "Extensions" : {
         "OccupancyData" : null,
         "LineColour" : "949494",
         "Deviations" : [
            {
               "Header" : "Feil i reiseplanlegger",
               "ID" : 42794
            }
         ],
         "IsHub" : false,
         "DepartureNamePreMapping" : "1"
      },
      "StopVisitNote" : [],
      "MonitoringRef" : "3011522",
      "MonitoredVehicleJourney" : {
         "TrainBlockPart" : null,
         "OriginName" : "Mortensrud T [buss]",
         "BlockRef" : null,
         "DirectionName" : null,
         "Delay" : null,
         "VehicleJourneyName" : "236060210",
         "DestinationRef" : "2350301",
         "MonitoredCall" : {
            "DestinationDisplay" : "Oslo lufthavn",
            "VehicleAtStop" : false,
            "AimedArrivalTime" : "2017-03-25T10:05:00+01:00",
            "DeparturePlatformName" : "1",
            "AimedDepartureTime" : "2017-03-25T10:05:00+01:00",
            "ExpectedArrivalTime" : "2017-03-25T10:05:00+01:00",
            "ExpectedDepartureTime" : "2017-03-25T10:05:00+01:00",
            "VisitNumber" : 0
         },
         "OriginRef" : "3010951",
         "InCongestion" : false,
         "VehicleFeatureRef" : null,
         "VehicleRef" : null,
         "PublishedLineName" : "FB6",
         "Monitored" : false,
         "FramedVehicleJourneyRef" : {
            "DataFrameRef" : "2017-03-25",
            "DatedVehicleJourneyRef" : "236060210"
         },
         "DestinationAimedArrivalTime" : "2017-03-25T10:44:00+01:00",
         "OperatorRef" : null,
         "DirectionRef" : null,
         "LineRef" : "3606",
         "OriginAimedDepartureTime" : "2017-03-25T09:40:00+01:00",
         "VehicleMode" : 0,
         "DestinationName" : "Oslo lufthavn"
      }
   },
   {
      "RecordedAtTime" : "2017-03-25T08:20:02.0668597+01:00",
      "MonitoringRef" : "3011522",
      "StopVisitNote" : [],
      "MonitoredVehicleJourney" : {
         "VehicleFeatureRef" : null,
         "InCongestion" : false,
         "MonitoredCall" : {
            "VisitNumber" : 0,
            "DestinationDisplay" : "Grorud T",
            "DeparturePlatformName" : "1",
            "VehicleAtStop" : false,
            "AimedArrivalTime" : "2017-03-25T10:07:00+01:00",
            "ExpectedArrivalTime" : "2017-03-25T10:07:00+01:00",
            "AimedDepartureTime" : "2017-03-25T10:07:00+01:00",
            "ExpectedDepartureTime" : "2017-03-25T10:07:00+01:00"
         },
         "OriginRef" : "3010921",
         "VehicleJourneyName" : "200790206",
         "DestinationRef" : "3011941",
         "BlockRef" : null,
         "DirectionName" : null,
         "OriginName" : "Holmlia stasjon [buss]",
         "Delay" : null,
         "TrainBlockPart" : null,
         "DestinationName" : "Grorud T",
         "LineRef" : "79",
         "OriginAimedDepartureTime" : "2017-03-25T09:29:00+01:00",
         "VehicleMode" : 0,
         "DirectionRef" : null,
         "DestinationAimedArrivalTime" : "2017-03-25T10:31:00+01:00",
         "OperatorRef" : null,
         "FramedVehicleJourneyRef" : {
            "DataFrameRef" : "2017-03-25",
            "DatedVehicleJourneyRef" : "200790206"
         },
         "PublishedLineName" : "79",
         "Monitored" : false,
         "VehicleRef" : null
      },
      "Extensions" : {
         "Deviations" : [],
         "LineColour" : "E60000",
         "OccupancyData" : null,
         "DepartureNamePreMapping" : "1",
         "IsHub" : false
      }
   },
   {
      "MonitoringRef" : "3011522",
      "StopVisitNote" : [],
      "MonitoredVehicleJourney" : {
         "MonitoredCall" : {
            "DeparturePlatformName" : "1",
            "VehicleAtStop" : false,
            "AimedArrivalTime" : "2017-03-25T10:07:00+01:00",
            "DestinationDisplay" : "Nydalen via Bjerke",
            "ExpectedDepartureTime" : "2017-03-25T10:07:00+01:00",
            "ExpectedArrivalTime" : "2017-03-25T10:07:00+01:00",
            "AimedDepartureTime" : "2017-03-25T10:07:00+01:00",
            "VisitNumber" : 0
         },
         "OriginRef" : "3011521",
         "VehicleJourneyName" : "100580237",
         "DestinationRef" : "3012135",
         "VehicleFeatureRef" : null,
         "InCongestion" : false,
         "TrainBlockPart" : null,
         "OriginName" : "Tveita T (foran senteret)",
         "BlockRef" : null,
         "DirectionName" : null,
         "Delay" : null,
         "DirectionRef" : null,
         "OperatorRef" : null,
         "DestinationAimedArrivalTime" : "2017-03-25T10:34:00+01:00",
         "DestinationName" : "Nydalen via Bjerke",
         "LineRef" : "58",
         "OriginAimedDepartureTime" : "2017-03-25T10:05:00+01:00",
         "VehicleMode" : 0,
         "Monitored" : false,
         "PublishedLineName" : "58",
         "VehicleRef" : null,
         "FramedVehicleJourneyRef" : {
            "DataFrameRef" : "2017-03-25",
            "DatedVehicleJourneyRef" : "100580237"
         }
      },
      "Extensions" : {
         "LineColour" : "E60000",
         "Deviations" : [
            {
               "ID" : 43009,
               "Header" : "Stoppestedet Nordpolen skole mot sentrum er flyttet"
            }
         ],
         "OccupancyData" : null,
         "DepartureNamePreMapping" : "1",
         "IsHub" : false
      },
      "RecordedAtTime" : "2017-03-25T08:20:02.0668597+01:00"
   },
   {
      "StopVisitNote" : [],
      "MonitoringRef" : "3011522",
      "MonitoredVehicleJourney" : {
         "TrainBlockPart" : null,
         "BlockRef" : null,
         "OriginName" : "Bøler T [buss]",
         "DirectionName" : null,
         "Delay" : null,
         "VehicleJourneyName" : "220610016",
         "DestinationRef" : "3011521",
         "MonitoredCall" : {
            "VisitNumber" : 0,
            "DestinationDisplay" : "Tveita T",
            "VehicleAtStop" : false,
            "AimedArrivalTime" : "2017-03-25T10:12:00+01:00",
            "DeparturePlatformName" : "2",
            "AimedDepartureTime" : "2017-03-25T10:12:00+01:00",
            "ExpectedArrivalTime" : "2017-03-25T10:12:00+01:00",
            "ExpectedDepartureTime" : "2017-03-25T10:12:00+01:00"
         },
         "OriginRef" : "3011121",
         "InCongestion" : false,
         "VehicleFeatureRef" : null,
         "VehicleRef" : null,
         "PublishedLineName" : "61B",
         "Monitored" : false,
         "FramedVehicleJourneyRef" : {
            "DatedVehicleJourneyRef" : "220610016",
            "DataFrameRef" : "2017-03-25"
         },
         "OperatorRef" : null,
         "DestinationAimedArrivalTime" : "2017-03-25T10:14:00+01:00",
         "DirectionRef" : null,
         "LineRef" : "2061",
         "OriginAimedDepartureTime" : "2017-03-25T10:00:00+01:00",
         "VehicleMode" : 0,
         "DestinationName" : "Tveita T"
      },
      "Extensions" : {
         "OccupancyData" : null,
         "LineColour" : "E60000",
         "Deviations" : [
            {
               "Header" : "Omkjøring via Bølerskogen og Utmarkveien",
               "ID" : 39505
            }
         ],
         "DepartureNamePreMapping" : "2",
         "IsHub" : false
      },
      "RecordedAtTime" : "2017-03-25T08:20:02.0668597+01:00"
   }
]
